setup.cfg
setup.py
tstk/__init__.py
tstk/bw_mean.py
tstk/collapse.py
tstk/common.py
tstk/counts2RPKM.py
tstk/dedup.py
tstk/fasta2ann.py
tstk/featurehist.py
tstk/filterset.py
tstk/getMGIannotations.py
tstk/get_overlapping_reads.py
tstk/gtf_parsing.py
tstk/io.py
tstk/peterplot.py
tstk/seqfeatfilter.py
tstk.egg-info/PKG-INFO
tstk.egg-info/SOURCES.txt
tstk.egg-info/dependency_links.txt
tstk.egg-info/entry_points.txt
tstk.egg-info/requires.txt
tstk.egg-info/top_level.txt