Metadata-Version: 1.1
Name: tstk
Version: 0.3.1
Summary: A bunch of tools for sequencing data analysis
Home-page: https://github.com/tdido/tstk
Author: Tomás Di Domenico
Author-email: tdido@tdido.com.ar
License: MIT
Keywords: sequence,toolkit,bioinformatics
Platform: UNKNOWN
Classifier: Development Status :: 4 - Beta
Classifier: Intended Audience :: Science/Research
Classifier: License :: OSI Approved :: MIT License
Classifier: Operating System :: OS Independent
Classifier: Programming Language :: Python :: 3
Classifier: Topic :: Scientific/Engineering :: Bio-Informatics
